say/__init__.py
aviHelloWorld-0.0.2.dist-info/METADATA
aviHelloWorld-0.0.2.dist-info/WHEEL
aviHelloWorld-0.0.2.dist-info/top_level.txt
aviHelloWorld-0.0.2.dist-info/RECORD
